pykotor
venv
