Metadata-Version: 2.1
Name: PyKotorGL
Version: 1.1.0
Summary: Render modules from both KotOR games.
Home-page: https://github.com/NickHugi/PyKotorGL
Author: Nicholas Hugi
License: UNKNOWN
Platform: UNKNOWN
License-File: LICENSE
Requires-Dist: numpy (==1.22.2)
Requires-Dist: PyGLM (==2.5.7)
Requires-Dist: PyOpenGL (==3.1.6)
Requires-Dist: PyKotor (==1.2.0)
Requires-Dist: setuptools (==57.4.0)
